ZAminofix/__init__.py
ZAminofix/acm.py
ZAminofix/client.py
ZAminofix/socket.py
ZAminofix/sub_client.py
ZAminofix/lib/__init__.py
ZAminofix/lib/util/__init__.py
ZAminofix/lib/util/exceptions.py
ZAminofix/lib/util/headers.py
ZAminofix/lib/util/helpers.py
ZAminofix/lib/util/objects.py
Sor-9.0.0.dist-info/LICENSE
Sor-9.0.0.dist-info/METADATA
Sor-9.0.0.dist-info/WHEEL
Sor-9.0.0.dist-info/top_level.txt
Sor-9.0.0.dist-info/RECORD
