Metadata-Version: 2.1
Name: Sor
Version: 9.0.0
Summary: By Sor. https://t.me/Tearedeyes
Author: Sorex
Keywords: ZAmino,ZAmino.fix,aminoapps,ZAminofix,amino,amino-bot
Requires-Python: >=3.6
License-File: LICENSE
Requires-Dist: httpx
Requires-Dist: websocket-client ==1.3.1
Requires-Dist: setuptools
Requires-Dist: json-minify
Requires-Dist: six
Requires-Dist: aiohttp
Requires-Dist: websockets
Requires-Dist: colorama
